<?xml version="1.0" encoding="utf-16"?><sketch label="ro"><stroke><point x="187.192306518555" y="143.884613037109" time="636008499803967880" /><point x="187.192306518555" y="143.884613037109" time="636008499804060637" /><point x="187.192306518555" y="143.884613037109" time="636008499804105735" /><point x="186.615386962891" y="143.615386962891" time="636008499804179841" /><point x="186.615386962891" y="143.615386962891" time="636008499804303119" /><point x="186.615386962891" y="143.615386962891" time="636008499804313071" /><point x="186.615386962891" y="143.615386962891" time="636008499804433089" /><point x="186.615386962891" y="143.615386962891" time="636008499804483090" /><point x="186.615386962891" y="143.615386962891" time="636008499804553108" /><point x="186.615386962891" y="143.615386962891" time="636008499804653103" /><point x="187" y="143.769226074219" time="636008499804703110" /><point x="187" y="143.769226074219" time="636008499804809616" /><point x="187.423080444336" y="143.923080444336" time="636008499804953907" /><point x="187.423080444336" y="143.923080444336" time="636008499804973893" /><point x="188.076919555664" y="144.076919555664" time="636008499805003875" /><point x="188.076919555664" y="144.076919555664" time="636008499805083922" /><point x="188.730773925781" y="144.076919555664" time="636008499805187959" /><point x="189.192306518555" y="144.076919555664" time="636008499805253255" /><point x="189.807693481445" y="144.076919555664" time="636008499805308696" /><point x="190.5" y="144.076919555664" time="636008499805423595" /><point x="191.346160888672" y="144.076919555664" time="636008499805448810" /><point x="192.346160888672" y="143.807693481445" time="636008499805568861" /><point x="193.423080444336" y="143.807693481445" time="636008499805611470" /><point x="194.730773925781" y="143.615386962891" time="636008499805704208" /><point x="196.230773925781" y="143.615386962891" time="636008499805799762" /><point x="197.846160888672" y="143.384613037109" time="636008499805834460" /><point x="199.615386962891" y="143.230773925781" time="636008499805944926" /><point x="201.423080444336" y="143.038467407227" time="636008499806004935" /><point x="203.346160888672" y="142.846160888672" time="636008499806064938" /><point x="205.346160888672" y="142.653839111328" time="636008499806175032" /><point x="207.423080444336" y="142.423080444336" time="636008499806200029" /><point x="209.423080444336" y="142.192306518555" time="636008499806315107" /><point x="211.423080444336" y="141.884613037109" time="636008499806365101" /><point x="213.423080444336" y="141.730773925781" time="636008499806465115" /><point x="215.346160888672" y="141.576919555664" time="636008499806555119" /><point x="217.192306518555" y="141.423080444336" time="636008499806595110" /><point x="219.192306518555" y="141.269226074219" time="636008499806695124" /><point x="221.076919555664" y="141.153839111328" time="636008499806755127" /><point x="223" y="141" time="636008499806815137" /><point x="224.923080444336" y="140.807693481445" time="636008499806895138" /><point x="226.923080444336" y="140.692306518555" time="636008499806955141" /><point x="228.846160888672" y="140.384613037109" time="636008499807075135" /><point x="230.807693481445" y="140.230773925781" time="636008499807115222" /><point x="232.807693481445" y="139.923080444336" time="636008499807225245" /><point x="234.730773925781" y="139.653839111328" time="636008499807315346" /><point x="236.576919555664" y="139.307693481445" time="636008499807345354" /><point x="238.307693481445" y="139.115386962891" time="636008499807455351" /><point x="239.923080444336" y="138.846160888672" time="636008499807525363" /><point x="241.615386962891" y="138.692306518555" time="636008499807585372" /><point x="243.230773925781" y="138.423080444336" time="636008499807685373" /><point x="244.807693481445" y="138.269226074219" time="636008499807715381" /><point x="246.307693481445" y="138.076919555664" time="636008499807825384" /><point x="247.846160888672" y="138.076919555664" time="636008499807875385" /><point x="249.423080444336" y="137.769226074219" time="636008499807975392" /><point x="251" y="137.615386962891" time="636008499808065409" /><point x="252.615386962891" y="137.384613037109" time="636008499808105388" /><point x="254.192306518555" y="137.230773925781" time="636008499808215500" /><point x="255.807693481445" y="137.153839111328" time="636008499808275612" /><point x="257.423065185547" y="137" time="636008499808335615" /><point x="259.115386962891" y="136.846160888672" time="636008499808455621" /><point x="260.692321777344" y="136.653839111328" time="636008499808475620" /><point x="262.192321777344" y="136.5" time="636008499808585637" /><point x="263.692321777344" y="136.307693481445" time="636008499808625641" /><point x="265.115386962891" y="136.230773925781" time="636008499808735650" /><point x="266.576934814453" y="136.076919555664" time="636008499808815652" /><point x="268" y="135.884613037109" time="636008499808845667" /><point x="269.423065185547" y="135.807693481445" time="636008499808965647" /><point x="270.692321777344" y="135.653839111328" time="636008499809025689" /><point x="272.076934814453" y="135.538467407227" time="636008499809085672" /><point x="273.423065185547" y="135.307693481445" time="636008499809210786" /><point x="274.730773925781" y="135.115386962891" time="636008499809225786" /><point x="275.923065185547" y="134.884613037109" time="636008499809335931" /><point x="277.192321777344" y="134.769226074219" time="636008499809385912" /><point x="278.423065185547" y="134.576919555664" time="636008499809465908" /><point x="279.692321777344" y="134.384613037109" time="636008499809575930" /><point x="280.807678222656" y="134.230773925781" time="636008499809605913" /><point x="281.923065185547" y="134.230773925781" time="636008499809725925" /><point x="283.115386962891" y="134.038467407227" time="636008499809785928" /><point x="284.307678222656" y="134.038467407227" time="636008499809835948" /><point x="285.576934814453" y="133.923080444336" time="636008499809955928" /><point x="286.692321777344" y="133.807693481445" time="636008499809965944" /><point x="287.923065185547" y="133.653839111328" time="636008499810075947" /><point x="289.076934814453" y="133.576919555664" time="636008499810126012" /><point x="290.307678222656" y="133.576919555664" time="636008499810216035" /><point x="291.615386962891" y="133.384613037109" time="636008499810316107" /><point x="292.923065185547" y="133.384613037109" time="636008499810346108" /><point x="294.307678222656" y="133.269226074219" time="636008499810456112" /><point x="295.692321777344" y="133.269226074219" time="636008499810516121" /><point x="297.192321777344" y="133.115386962891" time="636008499810576124" /><point x="298.692321777344" y="133.038467407227" time="636008499810686134" /><point x="300.230773925781" y="133.038467407227" time="636008499810716129" /><point x="301.923065185547" y="132.807693481445" time="636008499810826145" /><point x="303.576934814453" y="132.692306518555" time="636008499810876146" /><point x="305.307678222656" y="132.538467407227" time="636008499810966157" /><point x="307.076934814453" y="132.346160888672" time="636008499811066164" /><point x="308.730773925781" y="132.153839111328" time="636008499811106149" /><point x="310.5" y="132" time="636008499811211237" /><point x="312.192321777344" y="131.807693481445" time="636008499811276341" /><point x="313.923065185547" y="131.730773925781" time="636008499811326342" /><point x="315.615386962891" y="131.576919555664" time="636008499811446341" /><point x="317.307678222656" y="131.384613037109" time="636008499811466353" /><point x="318.923065185547" y="131.307693481445" time="636008499811596362" /><point x="320.576934814453" y="131.076919555664" time="636008499811646368" /><point x="322.230773925781" y="131.076919555664" time="636008499811736373" /><point x="323.923065185547" y="130.846160888672" time="636008499811836374" /><point x="325.576934814453" y="130.692306518555" time="636008499811856385" /><point x="326.923065185547" y="130.576919555664" time="636008499811986381" /><point x="328.423065185547" y="130.423080444336" time="636008499812036395" /><point x="329.807678222656" y="130.269226074219" time="636008499812096391" /><point x="331.192321777344" y="130.269226074219" time="636008499812221549" /><point x="332.423065185547" y="130.076919555664" time="636008499812246559" /><point x="333.692321777344" y="130.076919555664" time="636008499812351571" /><point x="334.807678222656" y="129.884613037109" time="636008499812406589" /><point x="336.076934814453" y="129.884613037109" time="636008499812491589" /><point x="337.346160888672" y="129.730773925781" time="636008499812586604" /><point x="338.692321777344" y="129.653839111328" time="636008499812621610" /><point x="339.730773925781" y="129.538467407227" time="636008499812726615" /><point x="340.923065185547" y="129.346160888672" time="636008499812801638" /><point x="342.192321777344" y="129.153839111328" time="636008499812851639" /><point x="343.576934814453" y="129" time="636008499812971664" /><point x="344.846160888672" y="128.730773925781" time="636008499812981648" /><point x="346.115386962891" y="128.423080444336" time="636008499813101673" /><point x="347.423065185547" y="128.192306518555" time="636008499813156678" /><point x="348.807678222656" y="127.923080444336" time="636008499813231682" /><point x="350.307678222656" y="127.653846740723" time="636008499813331708" /><point x="351.807678222656" y="127.384613037109" time="636008499813361703" /><point x="353.192321777344" y="127.076919555664" time="636008499813486714" /><point x="354.346160888672" y="126.807693481445" time="636008499813541757" /><point x="355.692321777344" y="126.576919555664" time="636008499813581716" /><point x="356.807678222656" y="126.5" time="636008499813696737" /><point x="357.807678222656" y="126.307693481445" time="636008499813721734" /><point x="358.615386962891" y="126.307693481445" time="636008499813841753" /><point x="359.192321777344" y="126.307693481445" time="636008499813891760" /><point x="359.692321777344" y="126.153846740723" time="636008499813976779" /><point x="359.692321777344" y="126.153846740723" time="636008499814076786" /><point x="360.307678222656" y="126.153846740723" time="636008499814111786" /><point x="360.307678222656" y="126.153846740723" time="636008499814211793" /><point x="360.307678222656" y="126.153846740723" time="636008499814286816" /><point x="360.307678222656" y="126.153846740723" time="636008499814331818" /><point x="360.307678222656" y="126.153846740723" time="636008499814441835" /><point x="360.307678222656" y="126.153846740723" time="636008499814496846" /><point x="360.307678222656" y="126.153846740723" time="636008499814591861" /><point x="360.307678222656" y="126.153846740723" time="636008499814641862" /><point x="360.307678222656" y="126.153846740723" time="636008499814721864" /><point x="360.307678222656" y="126.153846740723" time="636008499814816886" /><point x="360.307678222656" y="126.153846740723" time="636008499814856883" /><point x="360.307678222656" y="126.153846740723" time="636008499814961895" /><point x="360.307678222656" y="126.153846740723" time="636008499815051912" /><point x="360.307678222656" y="126.153846740723" time="636008499815086918" /><point x="360.076934814453" y="126.653846740723" time="636008499815191924" /><point x="360.076934814453" y="126.653846740723" time="636008499815251940" /><point x="359.692321777344" y="127.269233703613" time="636008499815326950" /><point x="359.692321777344" y="127.269233703613" time="636008499815436972" /><point x="359.076934814453" y="128.076919555664" time="636008499815466974" /><point x="358.692321777344" y="128.576919555664" time="636008499815576990" /><point x="358.307678222656" y="129.115386962891" time="636008499815627003" /><point x="358.076934814453" y="129.692306518555" time="636008499815722006" /><point x="357.730773925781" y="130.269226074219" time="636008499815817028" /><point x="357.307678222656" y="130.923080444336" time="636008499815852015" /><point x="356.923065185547" y="131.615386962891" time="636008499815957033" /><point x="356.346160888672" y="132.307693481445" time="636008499816017042" /><point x="355.923065185547" y="133.038467407227" time="636008499816077052" /><point x="355.423065185547" y="133.807693481445" time="636008499816192066" /><point x="354.807678222656" y="134.538467407227" time="636008499816212065" /><point x="354.230773925781" y="135.269226074219" time="636008499816332084" /><point x="353.615386962891" y="135.923080444336" time="636008499816372082" /><point x="353.076934814453" y="136.692306518555" time="636008499816477106" /><point x="352.5" y="137.384613037109" time="636008499816567104" /><point x="351.923065185547" y="138.192306518555" time="636008499816602123" /><point x="351.423065185547" y="139.076919555664" time="636008499816707129" /><point x="350.807678222656" y="139.846160888672" time="636008499816772155" /><point x="350.192321777344" y="140.769226074219" time="636008499816832146" /><point x="349.576934814453" y="141.730773925781" time="636008499816967165" /><point x="348.923065185547" y="142.653839111328" time="636008499816967165" /><point x="348.307678222656" y="143.692306518555" time="636008499817092182" /><point x="347.576934814453" y="144.730773925781" time="636008499817132180" /><point x="346.807678222656" y="145.807693481445" time="636008499817227189" /><point x="346.076934814453" y="147" time="636008499817327209" /><point x="345.307678222656" y="148.038467407227" time="636008499817357223" /><point x="344.615386962891" y="149.038467407227" time="636008499817467227" /><point x="343.846160888672" y="150.115386962891" time="636008499817532241" /><point x="343.076934814453" y="151.192306518555" time="636008499817587239" /><point x="342.230773925781" y="152.230773925781" time="636008499817697268" /><point x="341.423065185547" y="153.269226074219" time="636008499817717254" /><point x="340.692321777344" y="154.269226074219" time="636008499817827258" /><point x="340" y="155.192306518555" time="636008499817872273" /><point x="339.307678222656" y="156.153839111328" time="636008499817972286" /><point x="338.576934814453" y="157.038467407227" time="636008499818057293" /><point x="337.846160888672" y="158" time="636008499818092299" /><point x="337.192321777344" y="158.884613037109" time="636008499818202309" /><point x="336.423065185547" y="159.884613037109" time="636008499818262318" /><point x="335.730773925781" y="160.807693481445" time="636008499818327319" /><point x="335.076934814453" y="161.769226074219" time="636008499818437348" /><point x="334.192321777344" y="162.846160888672" time="636008499818462345" /><point x="333.307678222656" y="163.846160888672" time="636008499818577353" /><point x="332.346160888672" y="165" time="636008499818627367" /><point x="331.346160888672" y="165.923080444336" time="636008499818722369" /><point x="330.423065185547" y="167.076919555664" time="636008499818812387" /><point x="329.576934814453" y="168.115386962891" time="636008499818842382" /><point x="328.615386962891" y="169.269226074219" time="636008499818957409" /><point x="327.692321777344" y="170.307693481445" time="636008499819017418" /><point x="326.730773925781" y="171.5" time="636008499819077421" /><point x="325.807678222656" y="172.615386962891" time="636008499819187425" /><point x="325" y="173.769226074219" time="636008499819212428" /><point x="324.192321777344" y="174.884613037109" time="636008499819327443" /><point x="323.307678222656" y="176.038467407227" time="636008499819372451" /><point x="322.423065185547" y="177.153839111328" time="636008499819492483" /><point x="321.615386962891" y="178.230773925781" time="636008499819577496" /><point x="320.730773925781" y="179.346160888672" time="636008499819612502" /><point x="319.923065185547" y="180.307693481445" time="636008499819727516" /><point x="319.115386962891" y="181.307693481445" time="636008499819777523" /><point x="318.307678222656" y="182.192306518555" time="636008499819842524" /><point x="317.5" y="183.153839111328" time="636008499819982548" /><point x="316.692321777344" y="183.923080444336" time="636008499819982548" /><point x="315.807678222656" y="184.846160888672" time="636008499820092552" /><point x="314.846160888672" y="185.769226074219" time="636008499820137567" /><point x="314.192321777344" y="186.653839111328" time="636008499820252581" /><point x="313.307678222656" y="187.5" time="636008499820342592" /><point x="312.615386962891" y="188.230773925781" time="636008499820362591" /><point x="311.730773925781" y="189.153839111328" time="636008499820472614" /><point x="310.923065185547" y="189.884613037109" time="636008499820532610" /><point x="310" y="190.807693481445" time="636008499820592613" /><point x="309.115386962891" y="191.576919555664" time="636008499820712639" /><point x="308.115386962891" y="192.423080444336" time="636008499820732644" /><point x="307.076934814453" y="193.269226074219" time="636008499820852669" /><point x="306.076934814453" y="194.307693481445" time="636008499820892667" /><point x="304.923065185547" y="195.346160888672" time="636008499820987689" /><point x="303.923065185547" y="196.423080444336" time="636008499821077693" /><point x="302.807678222656" y="197.576919555664" time="636008499821117691" /><point x="301.730773925781" y="198.692306518555" time="636008499821217705" /><point x="300.692321777344" y="199.846160888672" time="636008499821282719" /><point x="299.807678222656" y="201" time="636008499821362721" /><point x="298.807678222656" y="202.192306518555" time="636008499821482733" /><point x="297.807678222656" y="203.192306518555" time="636008499821482733" /><point x="296.807678222656" y="204.307693481445" time="636008499821597760" /><point x="295.730773925781" y="205.423080444336" time="636008499821642763" /><point x="294.730773925781" y="206.423080444336" time="636008499821742770" /><point x="293.692321777344" y="207.538467407227" time="636008499821837785" /><point x="292.615386962891" y="208.615386962891" time="636008499821862776" /><point x="291.423065185547" y="209.692306518555" time="636008499821977797" /><point x="290.423065185547" y="210.692306518555" time="636008499822027791" /><point x="289.346160888672" y="211.807693481445" time="636008499822082802" /><point x="288.346160888672" y="212.923080444336" time="636008499822207812" /><point x="287.307678222656" y="214.076919555664" time="636008499822217834" /><point x="286.423065185547" y="215.153839111328" time="636008499822337840" /><point x="285.423065185547" y="216.307693481445" time="636008499822382843" /><point x="284.5" y="217.423080444336" time="636008499822472847" /><point x="283.615386962891" y="218.576919555664" time="636008499822572861" /><point x="282.615386962891" y="219.692306518555" time="636008499822607873" /><point x="281.692321777344" y="220.923080444336" time="636008499822712879" /><point x="280.692321777344" y="222.115386962891" time="636008499822772901" /><point x="279.692321777344" y="223.269226074219" time="636008499822837915" /><point x="278.807678222656" y="224.576919555664" time="636008499822947912" /><point x="277.923065185547" y="225.884613037109" time="636008499822975892" /><point x="277.076934814453" y="227.346160888672" time="636008499823083400" /><point x="276.192321777344" y="228.692306518555" time="636008499823133413" /><point x="275.307678222656" y="230.153839111328" time="636008499823218208" /><point x="274.576934814453" y="231.5" time="636008499823318677" /><point x="273.692321777344" y="232.807693481445" time="636008499823348723" /><point x="272.846160888672" y="234.153839111328" time="636008499823456789" /><point x="272.076934814453" y="235.423080444336" time="636008499823526885" /><point x="271.192321777344" y="236.615386962891" time="636008499823576866" /><point x="270.307678222656" y="237.923080444336" time="636008499823696423" /><point x="269.423065185547" y="239.307693481445" time="636008499823716960" /><point x="268.576934814453" y="240.538467407227" time="636008499823837031" /><point x="267.576934814453" y="242" time="636008499823887025" /><point x="266.576934814453" y="243.269226074219" time="636008499823977145" /><point x="265.5" y="244.692306518555" time="636008499824072975" /><point x="264.423065185547" y="246.153839111328" time="636008499824106088" /><point x="263.192321777344" y="247.615386962891" time="636008499824206551" /><point x="261.923065185547" y="248.923080444336" time="636008499824276691" /><point x="260.576934814453" y="250.423080444336" time="636008499824336752" /><point x="259.076934814453" y="251.923080444336" time="636008499824448482" /><point x="257.615386962891" y="253.5" time="636008499824478464" /><point x="256" y="255.153839111328" time="636008499824588480" /><point x="254.346160888672" y="256.653839111328" time="636008499824640662" /><point x="252.615386962891" y="258.307678222656" time="636008499824717918" /><point x="251" y="259.923065185547" time="636008499824827947" /><point x="249.307693481445" y="261.538452148438" time="636008499824857936" /><point x="247.692306518555" y="263.153839111328" time="636008499824968035" /><point x="246.076919555664" y="264.692321777344" time="636008499825038041" /><point x="244.5" y="266.153839111328" time="636008499825088144" /><point x="242.923080444336" y="267.576934814453" time="636008499825198224" /><point x="241.307693481445" y="269.038452148438" time="636008499825218294" /><point x="239.846160888672" y="270.423065185547" time="636008499825348302" /><point x="238.346160888672" y="271.769226074219" time="636008499825388448" /><point x="236.923080444336" y="273.115386962891" time="636008499825475629" /><point x="235.423080444336" y="274.423065185547" time="636008499825578607" /><point x="234" y="275.769226074219" time="636008499825608628" /><point x="232.576919555664" y="277.192321777344" time="636008499825715962" /><point x="231.192306518555" y="278.538452148438" time="636008499825785955" /><point x="229.807693481445" y="279.846160888672" time="636008499825832228" /><point x="228.423080444336" y="281.192321777344" time="636008499825958348" /><point x="227.115386962891" y="282.653839111328" time="636008499825983364" /><point x="225.730773925781" y="284" time="636008499826094215" /><point x="224.576919555664" y="285.192321777344" time="636008499826144215" /><point x="223.307693481445" y="286.5" time="636008499826224211" /><point x="222.115386962891" y="287.730773925781" time="636008499826334220" /><point x="221.076919555664" y="288.846160888672" time="636008499826364228" /><point x="220.076919555664" y="290" time="636008499826474232" /><point x="219.192306518555" y="291.115386962891" time="636008499826534228" /><point x="218.192306518555" y="292.115386962891" time="636008499826594244" /><point x="217.307693481445" y="293.192321777344" time="636008499826704248" /><point x="216.423080444336" y="294.192321777344" time="636008499826734243" /><point x="215.615386962891" y="295.230773925781" time="636008499826844265" /><point x="214.692306518555" y="296.230773925781" time="636008499826904249" /><point x="213.807693481445" y="297.269226074219" time="636008499826984354" /><point x="212.846160888672" y="298.230773925781" time="636008499827074365" /><point x="211.923080444336" y="299.230773925781" time="636008499827119450" /><point x="211" y="300.192321777344" time="636008499827219458" /><point x="210.076919555664" y="301.230773925781" time="636008499827289476" /><point x="209.076919555664" y="302.192321777344" time="636008499827339477" /><point x="208.076919555664" y="303.115386962891" time="636008499827459489" /><point x="207.115386962891" y="304.192321777344" time="636008499827519492" /><point x="206.076919555664" y="305.192321777344" time="636008499827579501" /><point x="204.923080444336" y="306.423065185547" time="636008499827699495" /><point x="203.692306518555" y="307.615386962891" time="636008499827719494" /><point x="202.423080444336" y="308.884613037109" time="636008499827839500" /><point x="201.076919555664" y="310.076934814453" time="636008499827879497" /><point x="199.576919555664" y="311.346160888672" time="636008499827989674" /><point x="198.076919555664" y="312.692321777344" time="636008499828069689" /><point x="196.615386962891" y="313.923065185547" time="636008499828099780" /><point x="195.192306518555" y="315.153839111328" time="636008499828209777" /><point x="193.692306518555" y="316.269226074219" time="636008499828269767" /><point x="192.307693481445" y="317.538452148438" time="636008499828339767" /><point x="190.923080444336" y="318.692321777344" time="636008499828439787" /><point x="189.576919555664" y="319.846160888672" time="636008499828479778" /><point x="188.230773925781" y="321" time="636008499828589788" /><point x="186.923080444336" y="322.230773925781" time="636008499828639801" /><point x="185.692306518555" y="323.346160888672" time="636008499828729793" /><point x="184.346160888672" y="324.538452148438" time="636008499828829800" /><point x="183.076919555664" y="325.769226074219" time="636008499828859814" /><point x="181.807693481445" y="326.923065185547" time="636008499828964922" /><point x="180.346160888672" y="328.230773925781" time="636008499829024932" /><point x="178.923080444336" y="329.384613037109" time="636008499829090035" /><point x="177.5" y="330.692321777344" time="636008499829200052" /><point x="176.076919555664" y="332.038452148438" time="636008499829220063" /><point x="174.615386962891" y="333.5" time="636008499829340063" /><point x="173.115386962891" y="334.846160888672" time="636008499829380061" /><point x="171.692306518555" y="336.307678222656" time="636008499829490071" /><point x="170.192306518555" y="337.692321777344" time="636008499829580075" /><point x="168.807693481445" y="339.115386962891" time="636008499829610070" /><point x="167.5" y="340.5" time="636008499829730076" /><point x="166.230773925781" y="341.769226074219" time="636008499829780083" /><point x="165" y="343.076934814453" time="636008499829840092" /><point x="163.692306518555" y="344.230773925781" time="636008499829945213" /><point x="162.5" y="345.423065185547" time="636008499829970223" /><point x="161.346160888672" y="346.423065185547" time="636008499830080233" /><point x="160.307693481445" y="347.423065185547" time="636008499830125242" /><point x="159.307693481445" y="348.423065185547" time="636008499830225242" /><point x="158.423080444336" y="349.269226074219" time="636008499830310319" /><point x="157.5" y="350.153839111328" time="636008499830350317" /><point x="156.692306518555" y="350.884613037109" time="636008499830450318" /><point x="156.076919555664" y="351.538452148438" time="636008499830520324" /><point x="155.423080444336" y="352.192321777344" time="636008499830580333" /><point x="154.807693481445" y="352.692321777344" time="636008499830690343" /><point x="154.307693481445" y="353.192321777344" time="636008499830710329" /><point x="153.846160888672" y="353.615386962891" time="636008499830830341" /><point x="153.5" y="353.923065185547" time="636008499830870345" /><point x="153.5" y="353.923065185547" time="636008499830980349" /><point x="153" y="354.5" time="636008499831070360" /><point x="153" y="354.5" time="636008499831100361" /><point x="153" y="354.5" time="636008499831210435" /><point x="152.692306518555" y="354.846160888672" time="636008499831270753" /><point x="152.692306518555" y="354.846160888672" time="636008499831330846" /><point x="152.692306518555" y="354.846160888672" time="636008499831440843" /><point x="152.692306518555" y="354.846160888672" time="636008499831470863" /><point x="152.5" y="355.230773925781" time="636008499831580854" /><point x="152.5" y="355.230773925781" time="636008499831630867" /><point x="152.5" y="355.230773925781" time="636008499831730862" /><point x="152.307693481445" y="355.653839111328" time="636008499831820866" /><point x="152.307693481445" y="355.653839111328" time="636008499831851047" /><point x="152.307693481445" y="355.653839111328" time="636008499831958170" /><point x="152.307693481445" y="355.653839111328" time="636008499832018166" /><point x="152.076919555664" y="356.038452148438" time="636008499832085150" /><point x="152.076919555664" y="356.038452148438" time="636008499832198503" /><point x="152.076919555664" y="356.038452148438" time="636008499832223500" /><point x="152.076919555664" y="356.038452148438" time="636008499832329480" /><point x="152.076919555664" y="356.038452148438" time="636008499832379487" /><point x="152.076919555664" y="356.038452148438" time="636008499832479488" /><point x="152.076919555664" y="356.038452148438" time="636008499832569634" /><point x="152.076919555664" y="356.038452148438" time="636008499832604396" /><point x="152.423080444336" y="355.769226074219" time="636008499832704775" /><point x="152.423080444336" y="355.769226074219" time="636008499832773632" /><point x="153.076919555664" y="355.384613037109" time="636008499832843644" /><point x="153.5" y="355.230773925781" time="636008499832946333" /><point x="154.076919555664" y="354.846160888672" time="636008499832966352" /><point x="154.692306518555" y="354.5" time="636008499833086403" /><point x="155.423080444336" y="354.115386962891" time="636008499833133631" /><point x="156.307693481445" y="353.730773925781" time="636008499833233632" /><point x="157.307693481445" y="353.307678222656" time="636008499833321615" /><point x="158.307693481445" y="352.769226074219" time="636008499833353766" /><point x="159.307693481445" y="352.384613037109" time="636008499833464488" /><point x="160.5" y="351.807678222656" time="636008499833524491" /><point x="161.692306518555" y="351.307678222656" time="636008499833584616" /><point x="163.076919555664" y="350.730773925781" time="636008499833694665" /><point x="164.346160888672" y="350.076934814453" time="636008499833724673" /><point x="165.730773925781" y="349.384613037109" time="636008499833844679" /><point x="167.192306518555" y="348.807678222656" time="636008499833884676" /><point x="168.692306518555" y="348.153839111328" time="636008499833984684" /><point x="170.230773925781" y="347.538452148438" time="636008499834074682" /><point x="171.807693481445" y="346.923065185547" time="636008499834104690" /><point x="173.346160888672" y="346.269226074219" time="636008499834219794" /><point x="174.923080444336" y="345.846160888672" time="636008499834279803" /><point x="176.423080444336" y="345.307678222656" time="636008499834334885" /><point x="177.846160888672" y="344.884613037109" time="636008499834454891" /><point x="179.307693481445" y="344.384613037109" time="636008499834474897" /><point x="180.615386962891" y="344" time="636008499834594896" /><point x="181.923080444336" y="343.615386962891" time="636008499834634920" /><point x="183.192306518555" y="343.115386962891" time="636008499834724898" /><point x="184.346160888672" y="342.730773925781" time="636008499834825355" /><point x="185.576919555664" y="342.346160888672" time="636008499834855343" /><point x="186.692306518555" y="342" time="636008499834965777" /><point x="187.846160888672" y="341.615386962891" time="636008499835025780" /><point x="189" y="341.230773925781" time="636008499835085776" /><point x="190.192306518555" y="340.807678222656" time="636008499835207245" /><point x="191.230773925781" y="340.423065185547" time="636008499835227251" /><point x="192.307693481445" y="340.076934814453" time="636008499835342169" /><point x="193.423080444336" y="339.538452148438" time="636008499835392176" /><point x="194.5" y="339" time="636008499835476797" /><point x="195.692306518555" y="338.538452148438" time="636008499835582393" /><point x="196.807693481445" y="337.846160888672" time="636008499835612368" /><point x="198" y="337.307678222656" time="636008499835722378" /><point x="199.192306518555" y="336.807678222656" time="636008499835782368" /><point x="200.307693481445" y="336.192321777344" time="636008499835842384" /><point x="201.423080444336" y="335.615386962891" time="636008499835952394" /><point x="202.692306518555" y="335.153839111328" time="636008499835982396" /><point x="203.807693481445" y="334.653839111328" time="636008499836102389" /><point x="204.923080444336" y="334.230773925781" time="636008499836152518" /><point x="206.076919555664" y="333.730773925781" time="636008499836237530" /><point x="207.230773925781" y="333.269226074219" time="636008499836327631" /><point x="208.423080444336" y="332.769226074219" time="636008499836367642" /><point x="209.692306518555" y="332.307678222656" time="636008499836477626" /><point x="210.923080444336" y="331.846160888672" time="636008499836537866" /><point x="212.192306518555" y="331.307678222656" time="636008499836587880" /><point x="213.576919555664" y="330.807678222656" time="636008499836707886" /><point x="214.846160888672" y="330.269226074219" time="636008499836727878" /><point x="216.307693481445" y="329.730773925781" time="636008499836847903" /><point x="217.730773925781" y="329.192321777344" time="636008499836897897" /><point x="219.192306518555" y="328.615386962891" time="636008499836977893" /><point x="220.692306518555" y="328.192321777344" time="636008499837078522" /><point x="222.230773925781" y="327.653839111328" time="636008499837116178" /><point x="223.807693481445" y="327.153839111328" time="636008499837228196" /><point x="225.423080444336" y="326.576934814453" time="636008499837283201" /><point x="227" y="326.153839111328" time="636008499837335255" /><point x="228.576919555664" y="325.615386962891" time="636008499837461330" /><point x="230.076919555664" y="325.115386962891" time="636008499837481329" /><point x="231.5" y="324.653839111328" time="636008499837598333" /><point x="232.923080444336" y="324.153839111328" time="636008499837648320" /><point x="234.192306518555" y="323.730773925781" time="636008499837738331" /><point x="235.576919555664" y="323.307678222656" time="636008499837831287" /><point x="236.846160888672" y="323" time="636008499837871291" /><point x="238.076919555664" y="322.615386962891" time="636008499837971298" /><point x="239.307693481445" y="322.269226074219" time="636008499838051300" /><point x="240.423080444336" y="321.846160888672" time="636008499838091311" /><point x="241.692306518555" y="321.5" time="636008499838216418" /><point x="242.923080444336" y="321.115386962891" time="636008499838236423" /><point x="244.192306518555" y="320.730773925781" time="636008499838346516" /><point x="245.346160888672" y="320.307678222656" time="636008499838406519" /><point x="246.615386962891" y="319.807678222656" time="636008499838486656" /><point x="247.923080444336" y="319.423065185547" time="636008499838587099" /><point x="249.423080444336" y="318.923065185547" time="636008499838620116" /><point x="250.807693481445" y="318.692321777344" time="636008499838730120" /><point x="252.230773925781" y="318.269226074219" time="636008499838800132" /><point x="253.576919555664" y="317.884613037109" time="636008499838850139" /><point x="255" y="317.423065185547" time="636008499838960136" /><point x="256.423065185547" y="317.153839111328" time="636008499838990131" /><point x="257.730773925781" y="316.769226074219" time="636008499839100141" /><point x="259.076934814453" y="316.423065185547" time="636008499839150622" /><point x="260.230773925781" y="316.076934814453" time="636008499839245176" /><point x="261.5" y="315.692321777344" time="636008499839340448" /><point x="262.807678222656" y="315.307678222656" time="636008499839370462" /><point x="264.076934814453" y="314.923065185547" time="636008499839480575" /><point x="265.230773925781" y="314.576934814453" time="636008499839547975" /><point x="266.5" y="314.192321777344" time="636008499839597514" /><point x="267.807678222656" y="313.807678222656" time="636008499839697495" /><point x="269.115386962891" y="313.423065185547" time="636008499839767508" /><point x="270.5" y="313.076934814453" time="636008499839857506" /><point x="271.807678222656" y="312.730773925781" time="636008499839907538" /><point x="273.192321777344" y="312.5" time="636008499839983209" /><point x="274.576934814453" y="312.153839111328" time="636008499840077827" /><point x="276" y="311.807678222656" time="636008499840127840" /><point x="277.423065185547" y="311.576934814453" time="636008499840233102" /><point x="278.923065185547" y="311.346160888672" time="636008499840323081" /><point x="280.423065185547" y="311" time="636008499840353108" /><point x="281.923065185547" y="310.692321777344" time="636008499840463105" /><point x="283.307678222656" y="310.384613037109" time="636008499840513099" /><point x="284.807678222656" y="310.076934814453" time="636008499840583118" /><point x="286.307678222656" y="309.846160888672" time="636008499840693121" /><point x="287.730773925781" y="309.576934814453" time="636008499840723129" /><point x="289.192321777344" y="309.307678222656" time="636008499840841499" /><point x="290.692321777344" y="309" time="636008499840883274" /><point x="292.115386962891" y="308.769226074219" time="636008499840973894" /><point x="293.576934814453" y="308.576934814453" time="636008499841073882" /><point x="295.076934814453" y="308.346160888672" time="636008499841103877" /><point x="296.423065185547" y="308.192321777344" time="636008499841206868" /><point x="297.923065185547" y="308" time="636008499841271908" /><point x="299.346160888672" y="307.807678222656" time="636008499841332315" /><point x="300.692321777344" y="307.615386962891" time="636008499841442325" /><point x="302" y="307.615386962891" time="636008499841472320" /><point x="303.423065185547" y="307.307678222656" time="636008499841592589" /><point x="304.846160888672" y="307.307678222656" time="636008499841628006" /><point x="306.230773925781" y="307.115386962891" time="636008499841732806" /><point x="307.576934814453" y="307.115386962891" time="636008499841819673" /><point x="308.923065185547" y="306.884613037109" time="636008499841849661" /><point x="310.192321777344" y="306.884613037109" time="636008499841959472" /><point x="311.576934814453" y="306.884613037109" time="636008499842016364" /><point x="312.923065185547" y="306.730773925781" time="636008499842086459" /><point x="314.076934814453" y="306.730773925781" time="636008499842201582" /><point x="315.230773925781" y="306.653839111328" time="636008499842223057" /><point x="316.307678222656" y="306.653839111328" time="636008499842333439" /><point x="317.423065185547" y="306.653839111328" time="636008499842383459" /><point x="318.5" y="306.653839111328" time="636008499842480790" /><point x="319.692321777344" y="306.5" time="636008499842570641" /><point x="320.730773925781" y="306.5" time="636008499842600623" /><point x="321.807678222656" y="306.346160888672" time="636008499842710652" /><point x="322.923065185547" y="306.346160888672" time="636008499842770649" /><point x="324" y="306.346160888672" time="636008499842840655" /><point x="325.076934814453" y="306.346160888672" time="636008499842946821" /><point x="326.230773925781" y="306.346160888672" time="636008499842967109" /><point x="327.230773925781" y="306.192321777344" time="636008499843091144" /><point x="328.307678222656" y="306.192321777344" time="636008499843131129" /><point x="329.346160888672" y="306.192321777344" time="636008499843236295" /><point x="330.423065185547" y="306.307678222656" time="636008499843322142" /><point x="331.423065185547" y="306.307678222656" time="636008499843352150" /><point x="332.576934814453" y="306.307678222656" time="636008499843463590" /><point x="333.692321777344" y="306.307678222656" time="636008499843525755" /><point x="334.692321777344" y="306.307678222656" time="636008499843602498" /><point x="335.730773925781" y="306.5" time="636008499843692624" /><point x="336.846160888672" y="306.5" time="636008499843722677" /><point x="337.923065185547" y="306.576934814453" time="636008499843839360" /><point x="338.807678222656" y="306.576934814453" time="636008499843877933" /><point x="339.730773925781" y="306.807678222656" time="636008499843987943" /><point x="340.576934814453" y="306.884613037109" time="636008499844077954" /><point x="341.576934814453" y="307.115386962891" time="636008499844107981" /><point x="342.5" y="307.269226074219" time="636008499844215867" /><point x="343.423065185547" y="307.423065185547" time="636008499844280926" /><point x="344.230773925781" y="307.615386962891" time="636008499844341231" /><point x="345.192321777344" y="307.615386962891" time="636008499844452171" /><point x="346.192321777344" y="307.807678222656" time="636008499844472176" /><point x="347.230773925781" y="307.807678222656" time="636008499844592189" /><point x="348.307678222656" y="308.038452148438" time="636008499844637909" /><point x="349.307678222656" y="308.038452148438" time="636008499844742357" /><point x="350.346160888672" y="308.230773925781" time="636008499844832355" /><point x="351.423065185547" y="308.346160888672" time="636008499844862363" /><point x="352.423065185547" y="308.538452148438" time="636008499844972360" /><point x="353.423065185547" y="308.730773925781" time="636008499845032363" /><point x="354.423065185547" y="308.923065185547" time="636008499845102375" /><point x="355.423065185547" y="309.192321777344" time="636008499845212770" /><point x="356.576934814453" y="309.5" time="636008499845227770" /><point x="357.692321777344" y="309.730773925781" time="636008499845347853" /><point x="358.730773925781" y="310.038452148438" time="636008499845388044" /><point x="359.846160888672" y="310.269226074219" time="636008499845488609" /><point x="361.076934814453" y="310.576934814453" time="636008499845579396" /><point x="362.192321777344" y="310.769226074219" time="636008499845609398" /><point x="363.346160888672" y="311" time="636008499845719504" /><point x="364.615386962891" y="311.192321777344" time="636008499845789336" /><point x="365.615386962891" y="311.346160888672" time="636008499845846138" /><point x="366.692321777344" y="311.576934814453" time="636008499845956154" /><point x="367.807678222656" y="311.730773925781" time="636008499845976146" /><point x="368.730773925781" y="311.923065185547" time="636008499846106149" /><point x="369.576934814453" y="312.115386962891" time="636008499846146230" /><point x="370.576934814453" y="312.307678222656" time="636008499846246256" /><point x="371.346160888672" y="312.5" time="636008499846336319" /><point x="372.230773925781" y="312.692321777344" time="636008499846366314" /><point x="373" y="312.884613037109" time="636008499846476323" /><point x="373.807678222656" y="313.192321777344" time="636008499846546323" /><point x="374.5" y="313.423065185547" time="636008499846616348" /><point x="375.307678222656" y="313.653839111328" time="636008499846736341" /><point x="376.192321777344" y="314.038452148438" time="636008499846746344" /><point x="376.846160888672" y="314.307678222656" time="636008499846866356" /><point x="377.692321777344" y="314.576934814453" time="636008499846906367" /><point x="378.423065185547" y="314.769226074219" time="636008499846996352" /><point x="379.423065185547" y="315.115386962891" time="636008499847096365" /><point x="380.192321777344" y="315.307678222656" time="636008499847136370" /><point x="380.923065185547" y="315.576934814453" time="636008499847241510" /><point x="381.692321777344" y="315.846160888672" time="636008499847306620" /><point x="382.576934814453" y="316.076934814453" time="636008499847366623" /><point x="383.307678222656" y="316.307678222656" time="636008499847486648" /><point x="384.076934814453" y="316.615386962891" time="636008499847496644" /><point x="384.807678222656" y="317" time="636008499847616650" /><point x="385.576934814453" y="317.230773925781" time="636008499847666657" /><point x="386.307678222656" y="317.615386962891" time="636008499847756668" /><point x="387.192321777344" y="317.923065185547" time="636008499847846654" /><point x="388" y="318.192321777344" time="636008499847886664" /><point x="388.730773925781" y="318.5" time="636008499847996668" /><point x="389.576934814453" y="318.730773925781" time="636008499848046687" /><point x="390.307678222656" y="319.076934814453" time="636008499848116674" /><point x="391.076934814453" y="319.307678222656" time="636008499848236814" /><point x="391.692321777344" y="319.615386962891" time="636008499848256820" /><point x="392.346160888672" y="319.846160888672" time="636008499848371834" /><point x="393.076934814453" y="320.192321777344" time="636008499848411838" /><point x="393.807678222656" y="320.576934814453" time="636008499848501849" /><point x="394.5" y="320.923065185547" time="636008499848601863" /><point x="395.192321777344" y="321.307678222656" time="636008499848641873" /><point x="396.115386962891" y="321.692321777344" time="636008499848736966" /><point x="396.846160888672" y="322.076934814453" time="636008499848796962" /><point x="397.730773925781" y="322.5" time="636008499848856959" /><point x="398.615386962891" y="322.846160888672" time="636008499848966962" /><point x="399.346160888672" y="323.230773925781" time="636008499848986961" /><point x="400.115386962891" y="323.576934814453" time="636008499849106967" /><point x="400.807678222656" y="323.884613037109" time="636008499849156981" /><point x="401.576934814453" y="324.153839111328" time="636008499849246979" /><point x="402.192321777344" y="324.5" time="636008499849336996" /><point x="402.807678222656" y="324.807678222656" time="636008499849376987" /><point x="403.346160888672" y="325.076934814453" time="636008499849476995" /><point x="403.923065185547" y="325.423065185547" time="636008499849552101" /><point x="404.423065185547" y="325.692321777344" time="636008499849602101" /><point x="405.115386962891" y="326" time="636008499849717206" /><point x="405.692321777344" y="326.346160888672" time="636008499849737198" /><point x="406.230773925781" y="326.730773925781" time="636008499849857217" /><point x="406.692321777344" y="327.076934814453" time="636008499849907224" /><point x="407.192321777344" y="327.346160888672" time="636008499849987213" /><point x="407.692321777344" y="327.730773925781" time="636008499850097235" /><point x="408.192321777344" y="328.115386962891" time="636008499850127224" /><point x="408.615386962891" y="328.576934814453" time="636008499850227225" /><point x="408.923065185547" y="328.923065185547" time="636008499850307233" /><point x="409.307678222656" y="329.346160888672" time="636008499850357240" /><point x="409.692321777344" y="329.769226074219" time="636008499850477240" /><point x="410.076934814453" y="330.269226074219" time="636008499850497245" /><point x="410.5" y="330.692321777344" time="636008499850627343" /><point x="410.923065185547" y="331.115386962891" time="636008499850682355" /><point x="411.346160888672" y="331.5" time="636008499850757448" /><point x="412" y="331.846160888672" time="636008499850857449" /><point x="412.576934814453" y="332.346160888672" time="636008499850887438" /><point x="413.192321777344" y="332.730773925781" time="636008499850997454" /><point x="413.807678222656" y="333.192321777344" time="636008499851057464" /><point x="414.423065185547" y="333.576934814453" time="636008499851107483" /><point x="415" y="334.076934814453" time="636008499851227470" /><point x="415.5" y="334.615386962891" time="636008499851247482" /><point x="416.076934814453" y="335.192321777344" time="636008499851367488" /><point x="416.576934814453" y="335.730773925781" time="636008499851427472" /><point x="417" y="336.307678222656" time="636008499851507486" /><point x="417.423065185547" y="336.846160888672" time="636008499851607622" /><point x="417.923065185547" y="337.423065185547" time="636008499851642615" /><point x="418.423065185547" y="338.076934814453" time="636008499851747742" /><point x="418.807678222656" y="338.615386962891" time="636008499851817754" /><point x="419.423065185547" y="339.192321777344" time="636008499851867755" /><point x="419.846160888672" y="339.730773925781" time="636008499851987748" /><point x="420.307678222656" y="340.269226074219" time="636008499852007760" /><point x="420.730773925781" y="340.807678222656" time="636008499852127759" /><point x="421.230773925781" y="341.384613037109" time="636008499852177760" /><point x="421.692321777344" y="342" time="636008499852267764" /><point x="422.192321777344" y="342.538452148438" time="636008499852347785" /><point x="422.807678222656" y="343.076934814453" time="636008499852387796" /><point x="423.230773925781" y="343.615386962891" time="636008499852507796" /><point x="423.807678222656" y="344.192321777344" time="636008499852582889" /><point x="424.346160888672" y="344.692321777344" time="636008499852622893" /><point x="424.923065185547" y="345.192321777344" time="636008499852727905" /><point x="425.423065185547" y="345.730773925781" time="636008499852787914" /><point x="426.076934814453" y="346.384613037109" time="636008499852857927" /><point x="426.576934814453" y="347" time="636008499852952929" /><point x="427.076934814453" y="347.692321777344" time="636008499852982931" /><point x="427.576934814453" y="348.269226074219" time="636008499853092947" /><point x="428.076934814453" y="348.884613037109" time="636008499853142960" /><point x="428.5" y="349.615386962891" time="636008499853237963" /><point x="429.076934814453" y="350.192321777344" time="636008499853327974" /><point x="429.423065185547" y="350.884613037109" time="636008499853357969" /><point x="429.846160888672" y="351.423065185547" time="636008499853468043" /><point x="430.307678222656" y="352.076934814453" time="636008499853528046" /><point x="430.692321777344" y="352.692321777344" time="636008499853588043" /><point x="431.076934814453" y="353.346160888672" time="636008499853698065" /><point x="431.423065185547" y="354.076934814453" time="636008499853728060" /><point x="431.807678222656" y="354.807678222656" time="636008499853838077" /><point x="432.115386962891" y="355.576934814453" time="636008499853888071" /><point x="432.5" y="356.346160888672" time="636008499853988084" /><point x="432.807678222656" y="357.153839111328" time="636008499854078076" /><point x="433.192321777344" y="357.884613037109" time="636008499854108077" /><point x="433.576934814453" y="358.769226074219" time="636008499854218094" /><point x="433.923065185547" y="359.538452148438" time="636008499854278174" /><point x="434.307678222656" y="360.346160888672" time="636008499854343194" /><point x="434.730773925781" y="361.230773925781" time="636008499854448244" /><point x="435.192321777344" y="362.038452148438" time="636008499854478246" /><point x="435.692321777344" y="362.807678222656" time="636008499854588249" /><point x="436.076934814453" y="363.692321777344" time="636008499854638256" /><point x="436.307678222656" y="364.576934814453" time="636008499854738263" /><point x="436.576934814453" y="365.346160888672" time="636008499854838277" /><point x="436.846160888672" y="366.269226074219" time="636008499854878268" /><point x="437.192321777344" y="367.038452148438" time="636008499854978288" /><point x="437.423065185547" y="367.846160888672" time="636008499855038285" /><point x="437.730773925781" y="368.615386962891" time="636008499855108297" /><point x="438" y="369.307678222656" time="636008499855218287" /><point x="438.346160888672" y="370.038452148438" time="636008499855243413" /><point x="438.807678222656" y="370.769226074219" time="636008499855363419" /><point x="439.192321777344" y="371.538452148438" time="636008499855398431" /><point x="439.576934814453" y="372.192321777344" time="636008499855508544" /><point x="439.923065185547" y="373.038452148438" time="636008499855588565" /><point x="440.346160888672" y="373.807678222656" time="636008499855628556" /><point x="440.730773925781" y="374.615386962891" time="636008499855728563" /><point x="441.115386962891" y="375.5" time="636008499855798569" /><point x="441.423065185547" y="376.269226074219" time="636008499855858578" /><point x="441.692321777344" y="377.192321777344" time="636008499855988587" /><point x="442" y="378.076934814453" time="636008499855988587" /><point x="442.192321777344" y="378.923065185547" time="636008499856108600" /><point x="442.346160888672" y="379.769226074219" time="636008499856158581" /><point x="442.576934814453" y="380.615386962891" time="636008499856258710" /><point x="442.730773925781" y="381.538452148438" time="636008499856353738" /><point x="442.846160888672" y="382.384613037109" time="636008499856378735" /><point x="443.076934814453" y="383.307678222656" time="636008499856488739" /><point x="443.076934814453" y="384.153839111328" time="636008499856553753" /><point x="443.307678222656" y="385.115386962891" time="636008499856613762" /><point x="443.307678222656" y="386.038452148438" time="636008499856733781" /><point x="443.5" y="387" time="636008499856753780" /><point x="443.5" y="388.038452148438" time="636008499856873799" /><point x="443.5" y="389" time="636008499856918801" /><point x="443.5" y="389.923065185547" time="636008499857018814" /><point x="443.5" y="390.923065185547" time="636008499857103821" /><point x="443.5" y="392" time="636008499857138827" /><point x="443.5" y="393.076934814453" time="636008499857243845" /><point x="443.346160888672" y="394.076934814453" time="636008499857308853" /><point x="443.230773925781" y="395.076934814453" time="636008499857378865" /><point x="443.230773925781" y="396.115386962891" time="636008499857503869" /><point x="443.076934814453" y="397.115386962891" time="636008499857508880" /><point x="442.923065185547" y="398.076934814453" time="636008499857603876" /><point x="442.923065185547" y="399.115386962891" time="636008499857653883" /><point x="442.730773925781" y="400.038452148438" time="636008499857748905" /><point x="442.615386962891" y="400.923065185547" time="636008499857843907" /><point x="442.5" y="401.769226074219" time="636008499857868904" /><point x="442.5" y="402.653839111328" time="636008499857978927" /><point x="442.307678222656" y="403.423065185547" time="636008499858048407" /><point x="442.192321777344" y="404.307678222656" time="636008499858103219" /><point x="442.076934814453" y="405.115386962891" time="636008499858213223" /><point x="441.923065185547" y="405.884613037109" time="636008499858233221" /><point x="441.692321777344" y="406.769226074219" time="636008499858353369" /><point x="441.692321777344" y="407.538452148438" time="636008499858403382" /><point x="441.423065185547" y="408.307678222656" time="636008499858503376" /><point x="441.307678222656" y="409.115386962891" time="636008499858593381" /><point x="441.076934814453" y="410" time="636008499858623382" /><point x="441.076934814453" y="410.807678222656" time="636008499858733379" /><point x="440.846160888672" y="411.692321777344" time="636008499858790380" /><point x="440.692321777344" y="412.615386962891" time="636008499858851351" /><point x="440.692321777344" y="413.538452148438" time="636008499858963697" /><point x="440.423065185547" y="414.5" time="636008499858993948" /><point x="440.230773925781" y="415.423065185547" time="636008499859104253" /><point x="440.076934814453" y="416.384613037109" time="636008499859154241" /><point x="439.807678222656" y="417.346160888672" time="636008499859244541" /><point x="439.576934814453" y="418.269226074219" time="636008499859338664" /><point x="439.346160888672" y="419.192321777344" time="636008499859368666" /><point x="439.192321777344" y="420.115386962891" time="636008499859478913" /><point x="438.923065185547" y="421.038452148438" time="636008499859538922" /><point x="438.615386962891" y="421.923065185547" time="636008499859599586" /><point x="438.423065185547" y="422.730773925781" time="636008499859709583" /><point x="438.230773925781" y="423.576934814453" time="636008499859739566" /><point x="438.115386962891" y="424.269226074219" time="636008499859859700" /><point x="437.923065185547" y="425.076934814453" time="636008499859899704" /><point x="437.730773925781" y="425.807678222656" time="636008499859995066" /><point x="437.576934814453" y="426.576934814453" time="636008499860095080" /><point x="437.307678222656" y="427.307678222656" time="636008499860126249" /><point x="437.192321777344" y="428.076934814453" time="636008499860230491" /><point x="436.846160888672" y="428.884613037109" time="636008499860294497" /><point x="436.692321777344" y="429.576934814453" time="636008499860354346" /><point x="436.307678222656" y="430.423065185547" time="636008499860474333" /><point x="435.923065185547" y="431.230773925781" time="636008499860494338" /><point x="435.5" y="432.076934814453" time="636008499860614357" /><point x="435.076934814453" y="432.884613037109" time="636008499860654362" /><point x="434.576934814453" y="433.769226074219" time="636008499860744366" /><point x="434.076934814453" y="434.692321777344" time="636008499860844373" /><point x="433.615386962891" y="435.538452148438" time="636008499860884390" /><point x="433.076934814453" y="436.384613037109" time="636008499860989466" /><point x="432.692321777344" y="437.230773925781" time="636008499861048924" /><point x="432.192321777344" y="438.115386962891" time="636008499861106700" /><point x="431.923065185547" y="439.038452148438" time="636008499861216505" /><point x="431.576934814453" y="439.846160888672" time="636008499861246506" /><point x="431.192321777344" y="440.730773925781" time="636008499861366506" /><point x="430.807678222656" y="441.653839111328" time="636008499861416494" /><point x="430.423065185547" y="442.423065185547" time="636008499861496508" /><point x="430.076934814453" y="443.346160888672" time="636008499861596516" /><point x="429.615386962891" y="444.307678222656" time="636008499861626524" /><point x="429.192321777344" y="445.192321777344" time="636008499861734525" /><point x="428.692321777344" y="446.076934814453" time="636008499861803838" /><point x="428.230773925781" y="446.884613037109" time="636008499861854165" /><point x="427.807678222656" y="447.653839111328" time="636008499861969334" /><point x="427.5" y="448.384613037109" time="636008499861999322" /><point x="427.192321777344" y="449.153839111328" time="636008499862106605" /><point x="426.807678222656" y="449.807678222656" time="636008499862166615" /><point x="426.576934814453" y="450.5" time="636008499862246944" /><point x="426.307678222656" y="451.115386962891" time="636008499862357230" /><point x="425.923065185547" y="451.769226074219" time="636008499862377229" /><point x="425.730773925781" y="452.384613037109" time="636008499862488201" /><point x="425.346160888672" y="453.115386962891" time="636008499862558213" /><point x="424.923065185547" y="453.730773925781" time="636008499862608207" /><point x="424.576934814453" y="454.384613037109" time="636008499862728219" /><point x="423.923065185547" y="455.153839111328" time="636008499862748225" /><point x="423.346160888672" y="455.769226074219" time="636008499862868231" /><point x="422.807678222656" y="456.5" time="636008499862918225" /><point x="422.307678222656" y="457.192321777344" time="636008499863003334" /><point x="421.615386962891" y="457.769226074219" time="636008499863103341" /><point x="421.076934814453" y="458.307678222656" time="636008499863133452" /><point x="420.576934814453" y="458.884613037109" time="636008499863236526" /><point x="420" y="459.423065185547" time="636008499863316528" /><point x="419.576934814453" y="460.038452148438" time="636008499863366541" /><point x="419.076934814453" y="460.576934814453" time="636008499863476538" /><point x="418.576934814453" y="461.153839111328" time="636008499863506539" /><point x="417.923065185547" y="461.730773925781" time="636008499863616549" /><point x="417.423065185547" y="462.423065185547" time="636008499863666549" /><point x="416.807678222656" y="463.076934814453" time="636008499863756548" /><point x="416.192321777344" y="463.692321777344" time="636008499863866570" /><point x="415.5" y="464.384613037109" time="636008499863896572" /><point x="414.730773925781" y="465.076934814453" time="636008499864006684" /><point x="414.076934814453" y="465.730773925781" time="636008499864081694" /><point x="413.423065185547" y="466.307678222656" time="636008499864121756" /><point x="412.730773925781" y="466.923065185547" time="636008499864241782" /><point x="412.076934814453" y="467.538452148438" time="636008499864261787" /><point x="411.307678222656" y="468.153839111328" time="636008499864381793" /><point x="410.576934814453" y="468.807678222656" time="636008499864421791" /><point x="409.846160888672" y="469.576934814453" time="636008499864511802" /><point x="409.192321777344" y="470.192321777344" time="636008499864611790" /><point x="408.423065185547" y="470.807678222656" time="636008499864641791" /><point x="407.692321777344" y="471.5" time="636008499864751807" /><point x="407" y="472.076934814453" time="636008499864821813" /><point x="406.307678222656" y="472.692321777344" time="636008499864871807" /><point x="405.615386962891" y="473.307678222656" time="636008499864981900" /><point x="404.923065185547" y="473.807678222656" time="636008499865041916" /><point x="404.230773925781" y="474.346160888672" time="636008499865132017" /><point x="403.576934814453" y="474.846160888672" time="636008499865182030" /><point x="402.923065185547" y="475.384613037109" time="636008499865262026" /><point x="402.076934814453" y="475.923065185547" time="636008499865362033" /><point x="401.230773925781" y="476.384613037109" time="636008499865402037" /><point x="400.423065185547" y="476.923065185547" time="636008499865502044" /><point x="399.5" y="477.538452148438" time="636008499865592049" /><point x="398.5" y="478.038452148438" time="636008499865632046" /><point x="397.5" y="478.615386962891" time="636008499865742069" /><point x="396.423065185547" y="479.307678222656" time="636008499865792063" /><point x="395.307678222656" y="479.923065185547" time="636008499865872059" /><point x="394.307678222656" y="480.538452148438" time="636008499865972200" /><point x="393.192321777344" y="481.115386962891" time="636008499865992187" /><point x="392" y="481.653839111328" time="636008499866122304" /><point x="390.923065185547" y="482.230773925781" time="636008499866152319" /><point x="389.807678222656" y="482.769226074219" time="636008499866262316" /><point x="388.692321777344" y="483.307678222656" time="636008499866352333" /><point x="387.423065185547" y="483.730773925781" time="636008499866382328" /><point x="386.346160888672" y="484.192321777344" time="636008499866492332" /><point x="385.192321777344" y="484.615386962891" time="636008499866542345" /><point x="384.115386962891" y="485.038452148438" time="636008499866612325" /><point x="382.923065185547" y="485.538452148438" time="636008499866732356" /><point x="381.730773925781" y="485.923065185547" time="636008499866752349" /><point x="380.615386962891" y="486.423065185547" time="636008499866862359" /><point x="379.576934814453" y="486.846160888672" time="636008499866912366" /><point x="378.615386962891" y="487.384613037109" time="636008499867012482" /><point x="377.692321777344" y="487.769226074219" time="636008499867102493" /><point x="376.692321777344" y="488.230773925781" time="636008499867132501" /><point x="375.807678222656" y="488.692321777344" time="636008499867232501" /><point x="374.846160888672" y="489.076934814453" time="636008499867292505" /><point x="373.923065185547" y="489.538452148438" time="636008499867357512" /><point x="372.923065185547" y="489.923065185547" time="636008499867467509" /><point x="372.076934814453" y="490.384613037109" time="636008499867492532" /><point x="371.076934814453" y="490.769226074219" time="636008499867607546" /><point x="370.192321777344" y="491.230773925781" time="636008499867652548" /><point x="369.230773925781" y="491.576934814453" time="636008499867752575" /><point x="368.307678222656" y="492" time="636008499867842579" /><point x="367.576934814453" y="492.423065185547" time="636008499867877585" /><point x="366.807678222656" y="492.730773925781" time="636008499867982584" /><point x="366.115386962891" y="493.192321777344" time="636008499868047605" /><point x="365.423065185547" y="493.576934814453" time="636008499868107595" /><point x="364.730773925781" y="493.923065185547" time="636008499868217618" /><point x="364.115386962891" y="494.230773925781" time="636008499868242627" /><point x="363.423065185547" y="494.692321777344" time="636008499868352721" /><point x="362.615386962891" y="495.076934814453" time="636008499868402708" /><point x="361.923065185547" y="495.423065185547" time="636008499868502722" /><point x="361.192321777344" y="495.807678222656" time="636008499868592720" /><point x="360.423065185547" y="496.115386962891" time="636008499868622721" /><point x="359.692321777344" y="496.384613037109" time="636008499868732731" /><point x="359.076934814453" y="496.769226074219" time="636008499868792728" /><point x="358.307678222656" y="497" time="636008499868862746" /><point x="357.730773925781" y="497.307678222656" time="636008499868962734" /><point x="357.192321777344" y="497.538452148438" time="636008499868992736" /><point x="356.576934814453" y="497.692321777344" time="636008499869122764" /><point x="355.923065185547" y="498" time="636008499869157879" /><point x="355.5" y="498.269226074219" time="636008499869267889" /><point x="354.923065185547" y="498.538452148438" time="636008499869342976" /><point x="354.346160888672" y="498.807678222656" time="636008499869382967" /><point x="353.807678222656" y="499.192321777344" time="636008499869492983" /><point x="353.192321777344" y="499.5" time="636008499869552980" /><point x="352.615386962891" y="499.807678222656" time="636008499869612996" /><point x="351.923065185547" y="500.153839111328" time="636008499869732989" /><point x="351.346160888672" y="500.538452148438" time="636008499869753001" /><point x="350.807678222656" y="500.807678222656" time="636008499869873013" /><point x="350.230773925781" y="501.076934814453" time="636008499869913011" /><point x="349.692321777344" y="501.307678222656" time="636008499870013018" /><point x="349.115386962891" y="501.538452148438" time="636008499870113006" /><point x="348.692321777344" y="501.807678222656" time="636008499870143014" /><point x="348.192321777344" y="501.923065185547" time="636008499870253152" /><point x="347.615386962891" y="502.115386962891" time="636008499870313155" /><point x="347.115386962891" y="502.307678222656" time="636008499870373165" /><point x="346.5" y="502.576934814453" time="636008499870483181" /><point x="345.846160888672" y="502.769226074219" time="636008499870508184" /><point x="345.192321777344" y="503" time="636008499870628203" /><point x="344.5" y="503.230773925781" time="636008499870673206" /><point x="343.692321777344" y="503.538452148438" time="636008499870778217" /><point x="342.923065185547" y="503.730773925781" time="636008499870858238" /><point x="342.230773925781" y="504" time="636008499870893232" /><point x="341.576934814453" y="504.269226074219" time="636008499871013244" /><point x="340.730773925781" y="504.5" time="636008499871063257" /><point x="340.076934814453" y="504.692321777344" time="636008499871143259" /><point x="339.423065185547" y="504.884613037109" time="636008499871228272" /><point x="338.692321777344" y="505.076934814453" time="636008499871253269" /><point x="338" y="505.307678222656" time="636008499871363279" /><point x="337.307678222656" y="505.5" time="636008499871413279" /><point x="336.576934814453" y="505.692321777344" time="636008499871503297" /><point x="335.923065185547" y="505.923065185547" time="636008499871593378" /><point x="335.230773925781" y="506.153839111328" time="636008499871633376" /><point x="334.307678222656" y="506.346160888672" time="636008499871743392" /><point x="333.423065185547" y="506.615386962891" time="636008499871803421" /><point x="332.615386962891" y="506.884613037109" time="636008499871863411" /><point x="331.807678222656" y="507.115386962891" time="636008499871973414" /><point x="330.846160888672" y="507.346160888672" time="636008499871993400" /><point x="329.923065185547" y="507.538452148438" time="636008499872113407" /><point x="328.807678222656" y="507.730773925781" time="636008499872163413" /><point x="327.807678222656" y="507.884613037109" time="636008499872263427" /><point x="326.807678222656" y="508.076934814453" time="636008499872353515" /><point x="325.846160888672" y="508.192321777344" time="636008499872403528" /><point x="324.807678222656" y="508.307678222656" time="636008499872503535" /><point x="323.807678222656" y="508.5" time="636008499872563647" /><point x="322.730773925781" y="508.615386962891" time="636008499872623644" /><point x="321.730773925781" y="508.846160888672" time="636008499872743637" /><point x="320.730773925781" y="509.153839111328" time="636008499872773658" /><point x="319.730773925781" y="509.423065185547" time="636008499872883668" /><point x="318.846160888672" y="509.730773925781" time="636008499872933668" /><point x="317.923065185547" y="510.076934814453" time="636008499873023666" /><point x="317.076934814453" y="510.307678222656" time="636008499873113677" /><point x="316.115386962891" y="510.576934814453" time="636008499873143679" /><point x="315.192321777344" y="510.846160888672" time="636008499873253701" /><point x="314.307678222656" y="511.038452148438" time="636008499873313698" /><point x="313.346160888672" y="511.192321777344" time="636008499873373829" /><point x="312.5" y="511.307678222656" time="636008499873488831" /><point x="311.423065185547" y="511.307678222656" time="636008499873508843" /><point x="310.423065185547" y="511.615386962891" time="636008499873633847" /><point x="309.346160888672" y="511.769226074219" time="636008499873678862" /><point x="308.307678222656" y="511.923065185547" time="636008499873768873" /><point x="307.307678222656" y="512.153869628906" time="636008499873868886" /><point x="306.307678222656" y="512.307678222656" time="636008499873903893" /><point x="305.192321777344" y="512.538452148438" time="636008499874008898" /><point x="304.192321777344" y="512.730773925781" time="636008499874083921" /><point x="303.115386962891" y="512.884643554688" time="636008499874133921" /><point x="302.076934814453" y="513.115356445313" time="636008499874208925" /><point x="301.076934814453" y="513.269226074219" time="636008499874273945" /><point x="299.923065185547" y="513.423095703125" time="636008499874388953" /><point x="298.730773925781" y="513.653869628906" time="636008499874438954" /><point x="297.692321777344" y="513.846130371094" time="636008499874518962" /><point x="296.423065185547" y="514.076904296875" time="636008499874623980" /><point x="295.192321777344" y="514.307678222656" time="636008499874638981" /><point x="294" y="514.576904296875" time="636008499874748991" /><point x="292.730773925781" y="514.692321777344" time="636008499874818996" /><point x="291.576934814453" y="514.846130371094" time="636008499874864005" /><point x="290.423065185547" y="515.038452148438" time="636008499874984018" /><point x="289.230773925781" y="515.038452148438" time="636008499875004016" /><point x="288.115386962891" y="515.230773925781" time="636008499875124106" /><point x="287.076934814453" y="515.230773925781" time="636008499875174106" /><point x="286.076934814453" y="515.230773925781" time="636008499875254121" /><point x="285.076934814453" y="515.230773925781" time="636008499875354103" /><point x="284.076934814453" y="515.346130371094" time="636008499875394126" /><point x="283" y="515.346130371094" time="636008499875504123" /><point x="282" y="515.346130371094" time="636008499875574122" /><point x="281.076934814453" y="515.346130371094" time="636008499875614126" /><point x="280.192321777344" y="515.346130371094" time="636008499875734139" /><point x="279.423065185547" y="515.538452148438" time="636008499875764140" /><point x="278.692321777344" y="515.538452148438" time="636008499875874221" /><point x="277.846160888672" y="515.538452148438" time="636008499875929232" /><point x="277.230773925781" y="515.538452148438" time="636008499876004236" /><point x="276.576934814453" y="515.538452148438" time="636008499876114336" /><point x="275.923065185547" y="515.538452148438" time="636008499876164336" /><point x="275.307678222656" y="515.692321777344" time="636008499876264362" /><point x="274.692321777344" y="515.692321777344" time="636008499876324353" /><point x="274" y="515.692321777344" time="636008499876374372" /><point x="273.230773925781" y="515.692321777344" time="636008499876504362" /><point x="272.576934814453" y="515.807678222656" time="636008499876514364" /><point x="271.807678222656" y="515.807678222656" time="636008499876634377" /><point x="271.076934814453" y="516" time="636008499876684371" /><point x="270.307678222656" y="516" time="636008499876774388" /><point x="269.5" y="516" time="636008499876879490" /><point x="268.692321777344" y="516.153869628906" time="636008499876909504" /><point x="267.807678222656" y="516.153869628906" time="636008499877014625" /><point x="266.846160888672" y="516.269226074219" time="636008499877084630" /><point x="265.923065185547" y="516.269226074219" time="636008499877134624" /><point x="265" y="516.423095703125" time="636008499877264652" /><point x="264.076934814453" y="516.423095703125" time="636008499877304637" /><point x="263.076934814453" y="516.653869628906" time="636008499877384652" /><point x="262.076934814453" y="516.653869628906" time="636008499877434652" /><point x="261" y="516.846130371094" time="636008499877524657" /><point x="260" y="516.846130371094" time="636008499877614655" /><point x="258.923065185547" y="517.038452148438" time="636008499877664649" /><point x="257.846160888672" y="517.038452148438" time="636008499877754679" /><point x="256.807678222656" y="517.192321777344" time="636008499877859787" /><point x="255.692306518555" y="517.192321777344" time="636008499877879786" /><point x="254.576919555664" y="517.192321777344" time="636008499878004803" /><point x="253.615386962891" y="517.269226074219" time="636008499878054913" /><point x="252.692306518555" y="517.269226074219" time="636008499878124918" /><point x="251.807693481445" y="517.269226074219" time="636008499878254927" /><point x="250.923080444336" y="517.269226074219" time="636008499878254927" /><point x="250.230773925781" y="517.269226074219" time="636008499878364930" /><point x="249.615386962891" y="517.269226074219" time="636008499878404954" /><point x="249.192306518555" y="517.269226074219" time="636008499878504942" /><point x="248.730773925781" y="517.076904296875" time="636008499878604949" /><point x="248.730773925781" y="517.076904296875" time="636008499878644947" /><point x="248.192306518555" y="516.692321777344" time="636008499878724968" /><point x="248.615386962891" y="516.692321777344" time="636008499878784958" /><point x="248.615386962891" y="516.692321777344" time="636008499878895090" /><point x="249.5" y="516.192321777344" time="636008499878975098" /><point x="250.230773925781" y="516.076904296875" time="636008499879000108" /></stroke></sketch>